etcd/__init__.py
etcd/auth/__init__.py
etcd/auth/authpb/__init__.py
etcd/auth/authpb/auth_pb2.py
etcd/etcdserver/__init__.py
etcd/etcdserver/etcdserverpb/__init__.py
etcd/etcdserver/etcdserverpb/etcdserver_pb2.py
etcd/etcdserver/etcdserverpb/rpc_pb2.py
etcd/lease/__init__.py
etcd/lease/leasepb/__init__.py
etcd/lease/leasepb/lease_pb2.py
etcd/raft/__init__.py
etcd/raft/raftpb/__init__.py
etcd/raft/raftpb/raft_pb2.py
etcd/snap/__init__.py
etcd/snap/snappb/__init__.py
etcd/snap/snappb/snap_pb2.py
etcd/storage/__init__.py
etcd/storage/storagepb/__init__.py
etcd/storage/storagepb/kv_pb2.py
etcd/wal/__init__.py
etcd/wal/walpb/__init__.py
etcd/wal/walpb/record_pb2.py
etcd_apiv3-2.3.0.2.dist-info/DESCRIPTION.rst
etcd_apiv3-2.3.0.2.dist-info/METADATA
etcd_apiv3-2.3.0.2.dist-info/RECORD
etcd_apiv3-2.3.0.2.dist-info/WHEEL
etcd_apiv3-2.3.0.2.dist-info/metadata.json
etcd_apiv3-2.3.0.2.dist-info/top_level.txt
gogoproto/__init__.py
gogoproto/gogo_pb2.py
