Metadata-Version: 2.0
Name: etcd-apiv3
Version: 2.3.0.2
Summary: etcd apiv3 bindings for Python
Home-page: UNKNOWN
Author: spyzalski@mirantis.com
Author-email: UNKNOWN
License: UNKNOWN
Platform: UNKNOWN
Classifier: Topic :: Software Development :: Code Generators
Classifier: Topic :: Database
Classifier: Programming Language :: Python :: 2.7
Classifier: License :: OSI Approved :: Apache Software License
Requires-Dist: grpcio
Requires-Dist: protobuf (==3.0.0b2.post2)
